aiofs/__init__.py
aiofs/azure.py
aiofs/inmem.py
aiofs/os.py
aiofs/redis.py
aiofs-1.0.0.dist-info/METADATA
aiofs-1.0.0.dist-info/WHEEL
aiofs-1.0.0.dist-info/RECORD
