Metadata-Version: 2.4
Name: aiofs
Version: 1.0.0
Summary: Wrap data sources like files with asyncio python
Author-email: Salvador Ruiz <salvador.ruiz.r@gmail.com>
License: LGPL-3.0-or-later
Requires-Python: >=3.13
Provides-Extra: az
Requires-Dist: aiohttp>=3.13.2; extra == 'az'
Requires-Dist: azure-storage-blob>=12.27.1; extra == 'az'
Provides-Extra: os
Requires-Dist: aiofiles>=25.1.0; extra == 'os'
Provides-Extra: redis
Requires-Dist: redis>=7.1.0; extra == 'redis'
